os_flavor_selector/__init__.py
os_flavor_selector/flavors.py
os_flavor_selector/main.py
os_flavor_selector/utils.py
os_flavor_selector-0.0.3.dist-info/licenses/LICENSE
os_flavor_selector-0.0.3.dist-info/METADATA
os_flavor_selector-0.0.3.dist-info/WHEEL
os_flavor_selector-0.0.3.dist-info/entry_points.txt
os_flavor_selector-0.0.3.dist-info/top_level.txt
os_flavor_selector-0.0.3.dist-info/RECORD
