Metadata-Version: 2.4
Name: os-flavor-selector
Version: 0.0.3
Summary: A tool to filter OpenStack flavors based on resource criteria
Author: Thobias Salazar Trevisan
License: MIT License
Project-URL: Homepage, https://github.com/thobiast/openstack-flavor-selector
Project-URL: Source, https://github.com/thobiast/openstack-flavor-selector
Requires-Python: >=3.7
License-File: LICENSE
Requires-Dist: openstacksdk
Requires-Dist: rich
Dynamic: license-file
